trendvisualizer/__init__.py
trendvisualizer/chart_display.py
trendvisualizer/pie_charts.py
trendvisualizer/trend.py
trendvisualizer-1.0.2.dist-info/LICENSE
trendvisualizer-1.0.2.dist-info/METADATA
trendvisualizer-1.0.2.dist-info/WHEEL
trendvisualizer-1.0.2.dist-info/top_level.txt
trendvisualizer-1.0.2.dist-info/RECORD
