Metadata-Version: 2.1
Name: trendvisualizer
Version: 1.0.2
Summary: Visualize trend strength across various markets.
Home-page: https://github.com/GBERESEARCH/trendvisualizer
Author: GBERESEARCH
Author-email: gberesearch@gmail.com
License: MIT
License-File: LICENSE
Requires-Dist: numpy>=1.24.1
Requires-Dist: requests>=2.28.1
Requires-Dist: pandas>=1.5.2
Requires-Dist: matplotlib>=3.7.1
Requires-Dist: matplotlib-inline>=0.1.6
Requires-Dist: seaborn>=0.12.2
Requires-Dist: norgatedata>=1.0.64
Requires-Dist: yahoofinancials>=1.7
Requires-Dist: technicalmethods>=0.2.4
Requires-Dist: trendvisdata>=1.0.5
Requires-Dist: lxml>=4.9.2
